cybsi/cloud/__init__.py
cybsi/cloud/__version__.py
cybsi/cloud/api.py
cybsi/cloud/auth/__init__.py
cybsi/cloud/auth/api.py
cybsi/cloud/auth/api_key.py
cybsi/cloud/auth/limits.py
cybsi/cloud/auth/permission.py
cybsi/cloud/auth/resource.py
cybsi/cloud/auth/token.py
cybsi/cloud/client.py
cybsi/cloud/client_config.py
cybsi/cloud/enum.py
cybsi/cloud/error.py
cybsi/cloud/files/__init__.py
cybsi/cloud/files/files.py
cybsi/cloud/insight/__init__.py
cybsi/cloud/insight/api.py
cybsi/cloud/insight/schemas.py
cybsi/cloud/insight/task_queue.py
cybsi/cloud/insight/tasks.py
cybsi/cloud/internal/__init__.py
cybsi/cloud/internal/base.py
cybsi/cloud/internal/buffer.py
cybsi/cloud/internal/connector.py
cybsi/cloud/internal/multipart.py
cybsi/cloud/internal/time.py
cybsi/cloud/iocean/__init__.py
cybsi/cloud/iocean/api.py
cybsi/cloud/iocean/collection.py
cybsi/cloud/iocean/objects.py
cybsi/cloud/iocean/schemas.py
cybsi/cloud/pagination.py
cybsi/cloud/py.typed
cybsi/cloud/view.py
cybsi_cloud_sdk-1.1.4.dist-info/LICENSE
cybsi_cloud_sdk-1.1.4.dist-info/METADATA
cybsi_cloud_sdk-1.1.4.dist-info/WHEEL
cybsi_cloud_sdk-1.1.4.dist-info/RECORD
