Metadata-Version: 2.1
Name: cybsi-cloud-sdk
Version: 1.1.4
Summary: Cybsi Cloud development kit
License: Apache-2.0
Author: Cybsi Cloud developers
Requires-Python: >=3.8.1,<4
Classifier: License :: OSI Approved :: Apache Software License
Classifier: Programming Language :: Python :: 3
Classifier: Programming Language :: Python :: 3.9
Classifier: Programming Language :: Python :: 3.10
Classifier: Programming Language :: Python :: 3.11
Classifier: Programming Language :: Python :: 3.12
Requires-Dist: enum-tools (==0.11.0)
Requires-Dist: httpx (>=0.25.1,<0.26.0)
Requires-Dist: typing-extensions (>=4.8.0,<5.0.0)
